README.rst
setup.py
sklearntools/__init__.py
sklearntools/_tools.py
sklearntools.egg-info/PKG-INFO
sklearntools.egg-info/SOURCES.txt
sklearntools.egg-info/dependency_links.txt
sklearntools.egg-info/not-zip-safe
sklearntools.egg-info/requires.txt
sklearntools.egg-info/top_level.txt
test/test.py
test/test2.py