Metadata-Version: 2.1
Name: sklearntools
Version: 1.2.9
Summary: Tools of sklearn. Grid Search with multiprocess
Home-page: https://gitee.com/summry/sklearntools
Author: summy
Author-email: xiazhongbiao@126.com
License: UNKNOWN
Keywords: sklearn,Grid Search,machine learning
Platform: UNKNOWN
Requires-Python: >=3.6
